README.rst
setup.py
samspy/__init__.py
samspy/conversions.py
samspy.egg-info/PKG-INFO
samspy.egg-info/SOURCES.txt
samspy.egg-info/dependency_links.txt
samspy.egg-info/entry_points.txt
samspy.egg-info/requires.txt
samspy.egg-info/top_level.txt
samspy/cmds/__init__.py
samspy/cmds/lvbasic.py
samspy/cmds/sto.py
samspy/share/propellants.yaml
samspy/share/protolv.yaml
samspy/traj/__init__.py
samspy/traj/orbit.py
samspy/vehicle/__init__.py
samspy/vehicle/multistage.py
samspy/vehicle/propel.py
samspy/writers/ReportsLV1.py
samspy/writers/Text.py
samspy/writers/__init__.py