Metadata-Version: 1.1
Name: samspy
Version: 0.0.2
Summary: Simple Aerospace ModelS in Python
Home-page: https://github.com/kwan0xfff/SamsPy
Author: Rick Kwan
Author-email: kwan0xfff@gmail.com
License: Apache 2.0
Keywords: aerospace propulsion rocket-engines
Platform: UNKNOWN
Classifier: Development Status :: 2 - Pre-Alpha
Classifier: Intended Audience :: Science/Research
Classifier: Topic :: Scientific/Engineering
Classifier: License :: OSI Approved :: Apache Software License
Classifier: Programming Language :: Python :: 3
Classifier: Programming Language :: Python :: 3.3
Classifier: Programming Language :: Python :: 3.4
Classifier: Programming Language :: Python :: 3.5
Classifier: Programming Language :: Python :: 3.6
